colorteller/__init__.py
colorteller/command.py
colorteller/teller.py
colorteller/version.py
colorteller/visualize.py
colorteller/data/__init__.py
colorteller/data/dataset.py
colorteller/utils/__init__.py
colorteller/utils/benchmark.py
colorteller/utils/chart.py
colorteller/utils/cmd.py
colorteller/utils/color.py
colorteller/utils/hex.py
colorteller/utils/sort.py
colorteller-0.0.3.dist-info/METADATA
colorteller-0.0.3.dist-info/WHEEL
colorteller-0.0.3.dist-info/entry_points.txt
colorteller-0.0.3.dist-info/top_level.txt
colorteller-0.0.3.dist-info/RECORD
