Metadata-Version: 2.1
Name: colorteller
Version: 0.0.3
Summary: colorteller, benchmarking color palattes.
Home-page: https://github.com/kausalflow/colorteller-package
Author: L Ma
Author-email: hi@leima.is
License: MIT
Platform: UNKNOWN
Requires-Dist: colormath (>=3.0.0)
Requires-Dist: loguru (>=0.5.3)
Requires-Dist: matplotlib (>=3.5.0)
Requires-Dist: click (>=7.0.0)
Requires-Dist: seaborn (>=0.11.2)
Provides-Extra: all
Requires-Dist: mkdocs-material (>=0.4.4) ; extra == 'all'
Requires-Dist: nose (>=1.3.7) ; extra == 'all'
Requires-Dist: mkdocs-autorefs (>=0.1.1) ; extra == 'all'
Requires-Dist: mkdocstrings (>=0.15.0) ; extra == 'all'
Provides-Extra: docs
Requires-Dist: mkdocs-material (>=0.4.4) ; extra == 'docs'
Requires-Dist: mkdocstrings (>=0.15.0) ; extra == 'docs'
Requires-Dist: mkdocs-autorefs (>=0.1.1) ; extra == 'docs'
Provides-Extra: mkdocs-autorefs
Requires-Dist: mkdocs-autorefs (>=0.1.1) ; extra == 'mkdocs-autorefs'
Provides-Extra: mkdocs-material
Requires-Dist: mkdocs-material (>=0.4.4) ; extra == 'mkdocs-material'
Provides-Extra: mkdocstrings
Requires-Dist: mkdocstrings (>=0.15.0) ; extra == 'mkdocstrings'
Provides-Extra: nose
Requires-Dist: nose (>=1.3.7) ; extra == 'nose'
Provides-Extra: tests
Requires-Dist: nose (>=1.3.7) ; extra == 'tests'
